{
    "relation": [
        [
            "Date",
            "Aug 30",
            "Sep 8",
            "Sep 15",
            "Sep 22",
            "Sep 29",
            "Oct 5",
            "Oct 13",
            "Oct 20",
            "Oct 27",
            "Nov 3",
            "Nov 10"
        ],
        [
            "Opponent",
            "at Morehead State",
            "N.C. Wesleyan",
            "at Ferrum College",
            "at Ave Maria",
            "VU-Lynchburg",
            "vs. Apprentice",
            "at Brevard",
            "Concordia-Selma",
            "at Alfred State",
            "Webber Int'l",
            "at Edward Waters"
        ],
        [
            "Score",
            "L, 55-0",
            "W, 24-14",
            "L, 20-7",
            "L, 49-30",
            "L, 19-16",
            "W, 20-14",
            "L, 59-24",
            "L, 20-14",
            "W, 21-6",
            "W, 27-6",
            "W, 17-10"
        ],
        [
            "rush",
            "-",
            "-",
            "-",
            "-",
            "-",
            "-",
            "-",
            "-",
            "-",
            "-",
            "-"
        ],
        [
            "yds",
            "-",
            "-",
            "-",
            "-",
            "-",
            "-",
            "-",
            "-",
            "-",
            "-",
            "-"
        ],
        [
            "y/a",
            "-",
            "-",
            "-",
            "-",
            "-",
            "-",
            "-",
            "-",
            "-",
            "-",
            "-"
        ],
        [
            "lng",
            "-",
            "-",
            "-",
            "-",
            "-",
            "-",
            "-",
            "-",
            "-",
            "-",
            "-"
        ],
        [
            "td",
            "-",
            "-",
            "-",
            "-",
            "-",
            "-",
            "-",
            "-",
            "-",
            "-",
            "-"
        ],
        [
            "fum",
            "-",
            "-",
            "-",
            "-",
            "-",
            "-",
            "-",
            "-",
            "-",
            "-",
            "-"
        ],
        [
            "lost",
            "-",
            "-",
            "-",
            "-",
            "-",
            "-",
            "-",
            "-",
            "-",
            "-",
            "-"
        ]
    ],
    "pageTitle": "Xavier Fernandez | #50 | LB | Southern Virginia - Southern Virginia",
    "title": "",
    "url": "http://athletics.svu.edu/sports/fball/2012-13/players/xavierfernandez2xjz?view=gamelog&pos=rb",
    "hasHeader": true,
    "headerPosition": "FIRST_ROW",
    "tableType": "RELATION",
    "tableNum": 2,
    "s3Link": "common-crawl/crawl-data/CC-MAIN-2015-32/segments/1438042988311.72/warc/CC-MAIN-20150728002308-00311-ip-10-236-191-2.ec2.internal.warc.gz",
    "recordEndOffset": 16870471,
    "recordOffset": 16862269,
    "tableOrientation": "HORIZONTAL",
    "TableContextTimeStampAfterTable": "{15458=\u00a9 2012 Southern Virginia University \u00b7 One University Hill Drive, Buena Vista, VA 24416 \u00b7 800-229-8420}",
    "textBeforeTable": "Defense Scoring All-Purpose Returns Punting Kicking Receiving Rushing Passing Split Stats Career Stats Game Log Player Profile - - - 0 2 ffum int sac tk gp Xavier Fernandez\u00a0|\u00a0#50\u00a0|\u00a0 LB\u00a0|\u00a0 Southern Virginia Prospective Recruit ChecklistArchiveStrength & ConditioningNJAC StandingsStatistical LeadersStatisticsSchedule & ResultsRosterNewsCoachesHome",
    "textAfterTable": "\u00a9 2012 Southern Virginia University \u00b7 One University Hill Drive, Buena Vista, VA 24416 \u00b7 800-229-8420 View: Mobile | Desktop",
    "hasKeyColumn": true,
    "keyColumnIndex": 0,
    "headerRowIndex": 0
}