{
    "relation": [
        [
            "Name",
            "#81 MALCOLM SHIPMON",
            "#12 SASSIAN WILSON",
            "#22 CADEN PEREA",
            "Total:"
        ],
        [
            "Att",
            "3",
            "2",
            "1",
            "6"
        ],
        [
            "Yds",
            "44",
            "21",
            "20",
            "85"
        ],
        [
            "Avg",
            "14.7",
            "10.5",
            "20.0",
            "14.2"
        ],
        [
            "Lng",
            "18",
            "19",
            "20",
            "20"
        ],
        [
            "TD",
            "0",
            "0",
            "0",
            "0"
        ]
    ],
    "pageTitle": "Morgan vs Ben Lomond Game Stats | The Morgan County News - Morgan County, Utah",
    "title": "",
    "url": "http://morgannews.com/article/morgan-vs-ben-lomond-game-stats",
    "hasHeader": true,
    "headerPosition": "FIRST_ROW",
    "tableType": "RELATION",
    "tableNum": 25,
    "s3Link": "common-crawl/crawl-data/CC-MAIN-2015-32/segments/1438042989234.2/warc/CC-MAIN-20150728002309-00094-ip-10-236-191-2.ec2.internal.warc.gz",
    "recordEndOffset": 164437827,
    "recordOffset": 164419370,
    "tableOrientation": "HORIZONTAL",
    "TableContextTimeStampAfterTable": "{7892=Friday, September 16, 2011 (07:01 PM) League game at Morgan, 54084=Passing: BEN LOMOND SCOTS, #10 AUSTIN SULLINS 7-21-0-68, #23 NATE WATKINS 1-5-2-(minus 4); Morgan Trojans, #12 COLBY SKINNER 7-10-0-142, 51573=First quarter: MHS, #4 JOE KIPPEN 23 yd run (#20 STEPHEN DREDGE kick), 2:04 Second: No scoring Third: MHS, #23 KADE CARRIGAN 2 yd run (#20 STEPHEN DREDGE kick), 10:29; MHS, #34 BRIDGER ANDERSON 6 yd run (#20 STEPHEN DREDGE kick), 8:03; MHS, #23 KADE CARRIGAN 5 yd run (#20 STEPHEN DREDGE kick), 5:40; MHS, #12 COLBY SKINNER 17 yd pass to #1 ZACH KANE (#20 STEPHEN DREDGE kick), 2:12 Fourth: MHS, #12 COLBY SKINNER 16 yd pass to #41 BOSTON SAUNDERS (#20 STEPHEN DREDGE kick), 10:41; MHS, #28 CHRISTIAN WINN 34 yd run (#20 STEPHEN DREDGE kick), 0:35, 50407=Game start time: 7:01 PM; Game length: 0:00}",
    "lastModified": "Sun, 02 Aug 2015 20:28:12 GMT",
    "textBeforeTable": "Morgan Trojans 49, BEN LOMOND SCOTS 0 Friday, September 16, 2011 (07:01 PM) League game at Morgan 17 September, 2011 (All day) Article Date:\u00a0 22 September, 2011 - 03:31 Article | Morgan vs Ben Lomond Game Stats | Share } services_compact: 'print,favorites,email,facebook,twitter,digg,delicious,myspace,google,more' ui_508_compliant: true, { var addthis_config =",
    "textAfterTable": "#4 JOE KIPPEN 23 yd run (#20 STEPHEN DREDGE kick) 0 7 Morgan 3 10:29 #23 KADE CARRIGAN 2 yd run (#20 STEPHEN DREDGE kick) 0 14 Morgan 3 8:03 #34 BRIDGER ANDERSON 6 yd run (#20 STEPHEN DREDGE kick) 0 21 Morgan 3 5:40 #23 KADE CARRIGAN 5 yd run (#20 STEPHEN DREDGE kick) 0 28 Morgan 3 2:12 #12 COLBY SKINNER 17 yd pass to #1 ZACH KANE (#20 STEPHEN DREDGE kick) 0 35 Morgan 4 10:41 #12 COLBY SKINNER 16 yd pass to #41 BOSTON SAUNDERS (#20 STEPHEN DREDGE kick) 0 42 Morgan 4 0:35 #28 CHRISTIAN WINN 34 yd run (#20 STEPHEN DREDGE kick) 0 49 \u00a0 Team stats BEN LOMOND Morgan First downs 4 22 Rushing yardage 4 317 Pass completions - attempts 8-26 7-10 Passing yardage 64 142 Pass touchdowns -",
    "hasKeyColumn": true,
    "keyColumnIndex": 0,
    "headerRowIndex": 0
}