{
    "relation": [
        [
            "First Number",
            "1",
            "2",
            "3",
            "4",
            "5",
            "6",
            "7",
            "8",
            "9",
            "10",
            "11",
            "12",
            "13",
            "14",
            "15",
            "16",
            "17",
            "18",
            "19",
            "20"
        ],
        [
            "Indicates the Construction",
            "Half Wave Rectifiers",
            "Diodes. Single",
            "Triodes, Output",
            "Triodes, High-mu",
            "Tetrodes, Straight",
            "Tetrodes, Vari-mu",
            "Pentodes, Power and Video",
            "Pentodes, R.F. Straight",
            "Pentodes, R.F. Vari-mu",
            "Diodes, Double",
            "Triodes with Double Diode",
            "Pentodes, A.F. with Double Diode",
            "Triodes Double, High-mu",
            "Triodes Double, Class B Output",
            "Heptodes",
            "Triodes Output, D.C. Coupled",
            "Pentodes R.F. with Double Diode",
            "Pentodes with Triode",
            "",
            "Hexode/Heptode with Triode"
        ]
    ],
    "pageTitle": "Frank's Electron tube Pages - Tube Number Systems",
    "title": "",
    "url": "http://www.tubedata.info/tubnum.html",
    "hasHeader": true,
    "headerPosition": "FIRST_ROW",
    "tableType": "RELATION",
    "tableNum": 25,
    "s3Link": "common-crawl/crawl-data/CC-MAIN-2015-32/segments/1438042988065.26/warc/CC-MAIN-20150728002308-00292-ip-10-236-191-2.ec2.internal.warc.gz",
    "recordEndOffset": 803679508,
    "recordOffset": 803671306,
    "tableOrientation": "HORIZONTAL",
    "lastModified": "Wed, 27 Jul 2011 23:08:30 GMT",
    "textBeforeTable": "European system after 1934 (pro-electron) European system after 1934 Philips system before 1934 Mazda numbering system Russian numbering system Brimar type designation code Tesla numbering system \u00a0 Tube Number Systems \u00a0 Frank's Electron tube Pages",
    "textAfterTable": "tube systems A single detection diode B double detection diode C small-signal triode D power triode E small-signal tetrode (or 2nd emmission tube EE1) F small-signal pentode H hexode or heptode K octode L power pentode or power tetrode M indicator tube N thyratron Q enneode W single gasfilled rectifier diode X double gasfilled rectifier diode Y single vacuum rectifier diode Z double vacuum rectifier diode digits socket & order x P (some are V) (except U-series (e.g.UBL1), those are octal) 1x Y8A 2x W8A, Loctal (except D-series (e.g. DL21), those are octal) 3x K8A, A08, octal 4x",
    "hasKeyColumn": true,
    "keyColumnIndex": 1,
    "headerRowIndex": 0
}