{
    "relation": [
        [
            "Pos",
            "1 (6w)",
            "4 (5)"
        ],
        [
            "Dist",
            "",
            "0.5"
        ],
        [
            "Dog",
            "Rusheen Ben Age: 6 W: Bend pos: Adj: Sec:",
            "Power Woman Age: 6 W: Bend pos: Adj: Sec:"
        ],
        [
            "Trainer",
            "M E Wiley",
            "P W Young"
        ],
        [
            "Age",
            "6",
            "6"
        ],
        [
            "Weight",
            "",
            ""
        ],
        [
            "Bend Pos",
            "",
            ""
        ],
        [
            "Time",
            "",
            ""
        ],
        [
            "Adj",
            "",
            ""
        ],
        [
            "Sect",
            "",
            ""
        ],
        [
            "Comment",
            "",
            ""
        ],
        [
            "SP",
            "4/1",
            "5/2f"
        ]
    ],
    "pageTitle": "Power Woman Dog Profile | Greyhounds Racecards, Selections, Form & Live Results | Sporting Life",
    "title": "Thu 16th Feb 2012 15:07 Romford",
    "url": "http://www.sportinglife.com/greyhounds/profile/dog/power-woman/1537933",
    "hasHeader": true,
    "headerPosition": "FIRST_ROW",
    "tableType": "RELATION",
    "tableNum": 25,
    "s3Link": "common-crawl/crawl-data/CC-MAIN-2015-32/segments/1438042988311.72/warc/CC-MAIN-20150728002308-00002-ip-10-236-191-2.ec2.internal.warc.gz",
    "recordEndOffset": 719935518,
    "recordOffset": 719919124,
    "tableOrientation": "HORIZONTAL",
    "textBeforeTable": "Full Result 400m A8 Romford Sat 4th Aug 2012 10:31 Sat 4th Aug 2012 10:31 Romford Last 34 Runs Owner: Ms K P Cotton,mr C C Walker Trainer: P W Young Dam: Droopys Stacey Sire: Ace Hi Rumble Colour: bk Sex: b Date of Birth : 18-08-2008 (6) Power Woman 10:31\u00a0\u00a0 Kinsley 10:38\u00a0\u00a0 Swindon 10:46\u00a0\u00a0 Kinsley 10:53\u00a0\u00a0 Swindon 11:00\u00a0\u00a0 Kinsley 11:07\u00a0\u00a0 Swindon 11:16\u00a0\u00a0 Kinsley 11:23\u00a0\u00a0 Swindon 11:31\u00a0\u00a0 Kinsley 11:37\u00a0\u00a0 Swindon 11:44\u00a0\u00a0 Kinsley 11:51\u00a0\u00a0 Swindon 11:58\u00a0\u00a0 Kinsley 12:08\u00a0\u00a0 Swindon 12:17\u00a0\u00a0 Kinsley 12:24\u00a0\u00a0 Swindon 12:33\u00a0\u00a0 Kinsley 12:39\u00a0\u00a0 Swindon 12:47\u00a0\u00a0 Kinsley 12:57\u00a0\u00a0 Swindon 13:04\u00a0\u00a0 Kinsley 13:11\u00a0\u00a0 Swindon 13:19\u00a0\u00a0 Kinsley 13:27\u00a0\u00a0 Swindon 13:33\u00a0\u00a0 Kinsley 13:44\u00a0\u00a0 Swindon 13:49\u00a0\u00a0 Kinsley 13:58\u00a0\u00a0 Swindon 14:08\u00a0\u00a0 Hove 14:18\u00a0\u00a0 Monmore",
    "textAfterTable": "Sat 28th Jul 2012 13:49 Romford Sat 28th Jul 2012 13:49 Romford A8 400m Full Result Sat 28th Jul 2012 13:49 Romford Pos Dist Dog Trainer Age Weight Bend Pos Time Adj Sect Comment SP 1 (3) Power Woman Age: 6 W: 24.7 Bend pos: 1111 Adj: 25.1 Sec: 3.76 P W Young 6 24.7 1111 25.1 25.1 3.76 QAw,Mid,AlwaysLed 7/2 Wed 18th Jul 2012 19:30 Romford Wed 18th Jul 2012 19:30 Romford A8 400m Full Result Wed 18th Jul 2012 19:30 Romford",
    "hasKeyColumn": true,
    "keyColumnIndex": 3,
    "headerRowIndex": 0
}