{
    "relation": [
        [
            "",
            "LaMont Jordan",
            "Sammy Morris"
        ],
        [
            "Att",
            "4",
            "9"
        ],
        [
            "Yds",
            "14",
            "18"
        ],
        [
            "TD",
            "0",
            "0"
        ]
    ],
    "pageTitle": "New England Patriots at Buffalo Bills - December 28th, 2008 | Pro-Football-Reference.com",
    "title": "",
    "url": "http://www.pro-football-reference.com/boxscores/200812280buf.htm",
    "hasHeader": true,
    "headerPosition": "FIRST_ROW",
    "tableType": "RELATION",
    "tableNum": 25,
    "s3Link": "common-crawl/crawl-data/CC-MAIN-2015-32/segments/1438042988317.67/warc/CC-MAIN-20150728002308-00264-ip-10-236-191-2.ec2.internal.warc.gz",
    "recordEndOffset": 671507791,
    "recordOffset": 671475468,
    "tableOrientation": "HORIZONTAL",
    "TableContextTimeStampBeforeTable": "{1453=News: s-r blog:2015 NFL Schedule, 2212=Mobile Site You Are Here\u00a0>\u00a0PFR Home\u00a0>\u00a0Boxscores\u00a0>\u00a0New England Patriots at Buffalo Bills - December 28th, 2008}",
    "textBeforeTable": "Short Left (2/2, 20 yards) Deep Right (0/0, 0 yards) Deep Middle (0/0, 0 yards) Deep Left (0/0, 0 yards) New England Patriots Pass Targets DB Ko Simpson FS Donte Whitner SS Bryan Scott CB Terrence McGee WLB Keith Ellison MLB Paul Posluszny SLB Kawika Mitchell RDE Ryan Denney RDT Kyle Williams LDT Marcus Stroud LDE Chris Kelsay RT",
    "textAfterTable": "12 0 Short Middle (1/2, 14 yards) Tgt Catches Yds TD Wes Welker 2 1 14 0 Short Right (3/4, 44 yards) Tgt Catches",
    "hasKeyColumn": true,
    "keyColumnIndex": 0,
    "headerRowIndex": 0
}