{
    "relation": [
        [
            "Date",
            "11/14",
            "11/18",
            "11/21",
            "11/22",
            "11/23",
            "11/25",
            "11/29",
            "12/03",
            "12/06",
            "12/13",
            "12/16",
            "12/20",
            "12/27",
            "12/31",
            "01/03",
            "01/08",
            "01/10",
            "01/14",
            "01/17",
            "01/22",
            "01/24",
            "01/26",
            "01/31",
            "02/03",
            "02/06",
            "02/12",
            "02/14",
            "02/18",
            "02/21",
            "02/26",
            "02/28",
            "03/04"
        ],
        [
            "H/A/N",
            "Away",
            "Home",
            "Neutral",
            "Neutral",
            "Away",
            "Home",
            "Home",
            "Away",
            "Home",
            "Home",
            "Home",
            "Away",
            "Away",
            "Home",
            "Away",
            "Home",
            "Away",
            "Away",
            "Home",
            "Home",
            "Away",
            "Home",
            "Home",
            "Away",
            "Home",
            "Away",
            "Home",
            "Away",
            "Away",
            "Home",
            "Away",
            "Neutral"
        ],
        [
            "Opponent",
            "Duke",
            "",
            "American",
            "Morehead St",
            "LA Tech",
            "",
            "",
            "Wofford",
            "NC-Grnsboro",
            "",
            "Samford",
            "TN Martin",
            "VA Tech",
            "Gard-Webb",
            "Liberty",
            "Winthrop",
            "Radford",
            "Longwood",
            "Charl South",
            "Campbell",
            "Coastal Car",
            "High Point",
            "Longwood",
            "Campbell",
            "Liberty",
            "NC-Asheville",
            "Radford",
            "Charl South",
            "High Point",
            "Coastal Car",
            "Winthrop",
            "Longwood"
        ],
        [
            "Line",
            "+39.0",
            "--",
            "+13.5",
            "+15.0",
            "+29.0",
            "--",
            "--",
            "--",
            "--",
            "--",
            "--",
            "--",
            "--",
            "--",
            "--",
            "--",
            "--",
            "--",
            "--",
            "--",
            "--",
            "--",
            "--",
            "--",
            "--",
            "--",
            "--",
            "--",
            "--",
            "--",
            "--",
            "+3.0"
        ],
        [
            "Result",
            "L by 69",
            "W by 10",
            "L by 25",
            "L by 20",
            "L by 28",
            "W by 23",
            "W by 49",
            "L by 21",
            "L by 2",
            "W by 11",
            "L by 10",
            "L by 17",
            "L by 22",
            "L by 17",
            "W by 4",
            "L by 1",
            "L by 13",
            "W by 4",
            "L by 8",
            "W by 2",
            "L by 11",
            "L by 9",
            "L by 4",
            "L by 13",
            "W by 8",
            "W by 4",
            "L by 6",
            "L by 26",
            "L by 9",
            "W by 11",
            "L by 27",
            "L by 4"
        ],
        [
            "+/-",
            "-30.0",
            "--",
            "-11.5",
            "-5.0",
            "+1.0",
            "--",
            "--",
            "--",
            "--",
            "--",
            "--",
            "--",
            "--",
            "--",
            "--",
            "--",
            "--",
            "--",
            "--",
            "--",
            "--",
            "--",
            "--",
            "--",
            "--",
            "--",
            "--",
            "--",
            "--",
            "--",
            "--",
            "-1.0"
        ]
    ],
    "pageTitle": "2011-2012 NCAA BB Games: Catamounts Blue Hose",
    "title": "",
    "url": "https://www.teamrankings.com/ncaa-basketball/matchup/catamounts-blue-hose-2011-11-17/ats-analysis",
    "hasHeader": true,
    "headerPosition": "FIRST_ROW",
    "tableType": "RELATION",
    "tableNum": 4,
    "s3Link": "common-crawl/crawl-data/CC-MAIN-2015-32/segments/1438042988511.77/warc/CC-MAIN-20150728002308-00084-ip-10-236-191-2.ec2.internal.warc.gz",
    "recordEndOffset": 939263747,
    "recordOffset": 939248143,
    "tableOrientation": "HORIZONTAL",
    "TableContextTimeStampBeforeTable": "{3187=\u00a0 Thursday Nov 17, 2011 - 7:30 pm - Clinton, SC | Odds: N/A Total Points: N/A | Team Pages: WCAR | PRES}",
    "TableContextTimeStampAfterTable": "{33566=TeamRankings.com is not affiliated with the National Collegiate Athletic Association (NCAA\u00ae) or March Madness Athletic Association, neither of which has supplied, reviewed, approved or endorsed the material on this site. TeamRankings.com is solely responsible for this site but makes no guarantee about the accuracy or completeness of the information herein., 33366=\u00a9 2005-2015 Team Rankings, LLC. All Rights Reserved.}",
    "textBeforeTable": "W Carolina Detailed ATS Performance 1-4-0 10-8-0 Away 0-0-0 4-6-0 Home 0-1-0 5-5-0 Last 10 0-1-0 2-3-0 Last 5 L1 L1 Streak 0-1-0 11-9-0 vs Conference 0-0-0 0-0-0 vs Division 1-4-0 14-14-0 Season PRES adv WCAR Record ATS Situational Trends Predictions not yet available Confidence Model Pick ATS Predictions \u00a0 Thursday Nov 17, 2011 - 7:30 pm - Clinton, SC | Odds: N/A Total Points: N/A | Team Pages: WCAR | PRES W Carolina at Presbyterian 68 63 DUKE vs WISC Final NCAA Basketball Login Sign Up",
    "textAfterTable": "Presbyterian Detailed ATS Performance Date H/A/N Opponent Line Result +/- 11/14 Away Duke +39.0 L by 69 -30.0 11/18 Home -- W by 10 -- 11/21 Neutral American +13.5 L by 25 -11.5 11/22 Neutral Morehead St +15.0 L by 20 -5.0 11/23 Away LA Tech +29.0 L by 28 +1.0 11/25 Home -- W by 23 -- 11/29 Home -- W by 49 -- 12/03 Away Wofford -- L by 21 -- 12/06 Home NC-Grnsboro -- L by 2 -- 12/13 Home -- W by 11 -- 12/16 Home Samford -- L by 10 --",
    "hasKeyColumn": true,
    "keyColumnIndex": 4,
    "headerRowIndex": 0
}