{
    "relation": [
        [
            "SEC.",
            "01",
            "02",
            "03"
        ],
        [
            "CLASS #",
            "8887",
            "8888",
            "8889"
        ],
        [
            "CLASS NOTES",
            "",
            "",
            ""
        ],
        [
            "TYPE",
            "ACT",
            "ACT",
            "ACT"
        ],
        [
            "DAYS",
            "M",
            "Tu",
            "W"
        ],
        [
            "TIME",
            "4-6:45PM",
            "4-6:45PM",
            "4-6:45PM"
        ],
        [
            "OPEN SEATS as of 02/19",
            "",
            "",
            ""
        ],
        [
            "LOCATION",
            "HHS1-100",
            "HSD-111",
            "ET-229"
        ],
        [
            "INSTRUCTOR",
            "Sparks L",
            "Acosta-Deprez V",
            "Acosta-Deprez V"
        ],
        [
            "COMMENT",
            "Department Consent Required",
            "Department Consent Required",
            "Department Consent Required"
        ]
    ],
    "pageTitle": "Schedule of Classes",
    "title": "",
    "url": "http://web.csulb.edu/depts/enrollment/registration/class_schedule/Spring_2013/By_College/HzSC.html",
    "hasHeader": true,
    "headerPosition": "MIXED",
    "tableType": "RELATION",
    "tableNum": 25,
    "s3Link": "common-crawl/crawl-data/CC-MAIN-2015-32/segments/1438042989142.82/warc/CC-MAIN-20150728002309-00067-ip-10-236-191-2.ec2.internal.warc.gz",
    "recordEndOffset": 259456523,
    "recordOffset": 259442707,
    "tableOrientation": "HORIZONTAL",
    "TableContextTimeStampBeforeTable": "{1730=Class offerings as of : FEBRUARY 19, 2013}",
    "textBeforeTable": "1 Unit H SC 150 - MEDICAL TERMINOLOGY Health Science - (H SC) College of Health and Human Services By GE Requirement By College By Subject Textook Information Register Here Class offerings as of : FEBRUARY 19, 2013 Spring 2013 Schedule of Classes Home > Depts > Enrollment > Registration > Class Schedule > Spring 2013 > By College > Giving to CSULB Visitors & Community Parents",
    "textAfterTable": "Instructor Consent Required 04 10637 \u00a0 LEC M 12:30-1:20PM VEC-322 Nomura W Instructor Consent Required 05 10638 \u00a0 LEC W 12:30-1:20PM VEC-110 Nomura W Instructor Consent Required H SC 210 - CONTEMPORARY HEALTH ISSUES 3 Units GE AREA: B1aNL, E SEC. CLASS # CLASS NOTES TYPE DAYS TIME OPEN SEATS as of 02/19 LOCATION INSTRUCTOR COMMENT 01 1903 \u00a0 SEM MW 2-3:15PM ET-229 Whitehouse-Capuano N Instructor Consent Required 02 8881 \u00a0 SEM TuTh 9:30-10:45AM HSD-113 Nomura W Instructor Consent Required 03 8882 \u00a0 SEM MW 8-9:15AM VEC-227 Montano M Instructor Consent Required H SC 301 - ORIENTATION TO HEALTH SCIENCE 3 Units SEC. CLASS # CLASS NOTES TYPE DAYS TIME OPEN SEATS",
    "hasKeyColumn": false,
    "keyColumnIndex": -1,
    "headerRowIndex": 0
}